[
	{
		"anonymous": false,
		"inputs": [
			{
				"indexed": false,
				"internalType": "string",
				"name": "landId",
				"type": "string"
			},
			{
				"indexed": false,
				"internalType": "address",
				"name": "owner",
				"type": "address"
			},
			{
				"indexed": false,
				"internalType": "string",
				"name": "location",
				"type": "string"
			},
			{
				"indexed": false,
				"internalType": "uint256",
				"name": "area",
				"type": "uint256"
			},
			{
				"indexed": false,
				"internalType": "string",
				"name": "landUse",
				"type": "string"
			},
			{
				"indexed": false,
				"internalType": "string",
				"name": "documentHash",
				"type": "string"
			}
		],
		"name": "LandRegistered",
		"type": "event"
	},
	{
		"anonymous": false,
		"inputs": [
			{
				"indexed": false,
				"internalType": "string",
				"name": "landId",
				"type": "string"
			},
			{
				"indexed": false,
				"internalType": "address",
				"name": "from",
				"type": "address"
			},
			{
				"indexed": false,
				"internalType": "address",
				"name": "to",
				"type": "address"
			}
		],
		"name": "LandTransferred",
		"type": "event"
	},
	{
		"anonymous": false,
		"inputs": [
			{
				"indexed": false,
				"internalType": "string",
				"name": "landId",
				"type": "string"
			},
			{
				"indexed": false,
				"internalType": "address",
				"name": "verifier",
				"type": "address"
			}
		],
		"name": "LandVerified",
		"type": "event"
	},
	{
		"inputs": [
			{
				"internalType": "string",
				"name": "_landId",
				"type": "string"
			},
			{
				"internalType": "address",
				"name": "_owner",
				"type": "address"
			},
			{
				"internalType": "string",
				"name": "_location",
				"type": "string"
			},
			{
				"internalType": "uint256",
				"name": "_area",
				"type": "uint256"
			},
			{
				"internalType": "string",
				"name": "_landUse",
				"type": "string"
			},
			{
				"internalType": "string",
				"name": "_documentHash",
				"type": "string"
			}
		],
		"name": "registerLand",
		"outputs": [],
		"stateMutability": "nonpayable",
		"type": "function"
	},
	{
		"inputs": [
			{
				"internalType": "string",
				"name": "_landId",
				"type": "string"
			},
			{
				"internalType": "address",
				"name": "_newOwner",
				"type": "address"
			}
		],
		"name": "transferLand",
		"outputs": [],
		"stateMutability": "nonpayable",
		"type": "function"
	},
	{
		"inputs": [
			{
				"internalType": "string",
				"name": "_landId",
				"type": "string"
			}
		],
		"name": "verifyLand",
		"outputs": [],
		"stateMutability": "nonpayable",
		"type": "function"
	},
	{
		"inputs": [
			{
				"internalType": "string",
				"name": "_landId",
				"type": "string"
			}
		],
		"name": "getLandDetails",
		"outputs": [
			{
				"components": [
					{
						"internalType": "string",
						"name": "landId",
						"type": "string"
					},
					{
						"internalType": "address",
						"name": "owner",
						"type": "address"
					},
					{
						"internalType": "string",
						"name": "location",
						"type": "string"
					},
					{
						"internalType": "uint256",
						"name": "area",
						"type": "uint256"
					},
					{
						"internalType": "string",
						"name": "landUse",
						"type": "string"
					},
					{
						"internalType": "bool",
						"name": "isRegistered",
						"type": "bool"
					},
					{
						"internalType": "bool",
						"name": "isVerified",
						"type": "bool"
					},
					{
						"internalType": "string",
						"name": "documentHash",
						"type": "string"
					},
					{
						"internalType": "uint256",
						"name": "lastTransactionTimestamp",
						"type": "uint256"
					}
				],
				"internalType": "struct LandRegistry.Land",
				"name": "",
				"type": "tuple"
			}
		],
		"stateMutability": "view",
		"type": "function"
	},
	{
		"inputs": [
			{
				"internalType": "address",
				"name": "_owner",
				"type": "address"
			}
		],
		"name": "getOwnerLands",
		"outputs": [
			{
				"internalType": "string[]",
				"name": "",
				"type": "string[]"
			}
		],
		"stateMutability": "view",
		"type": "function"
	},
	{
		"inputs": [
			{
				"internalType": "string",
				"name": "",
				"type": "string"
			}
		],
		"name": "lands",
		"outputs": [
			{
				"internalType": "string",
				"name": "landId",
				"type": "string"
			},
			{
				"internalType": "address",
				"name": "owner",
				"type": "address"
			},
			{
				"internalType": "string",
				"name": "location",
				"type": "string"
			},
			{
				"internalType": "uint256",
				"name": "area",
				"type": "uint256"
			},
			{
				"internalType": "string",
				"name": "landUse",
				"type": "string"
			},
			{
				"internalType": "bool",
				"name": "isRegistered",
				"type": "bool"
			},
			{
				"internalType": "bool",
				"name": "isVerified",
				"type": "bool"
			},
			{
				"internalType": "string",
				"name": "documentHash",
				"type": "string"
			},
			{
				"internalType": "uint256",
				"name": "lastTransactionTimestamp",
				"type": "uint256"
			}
		],
		"stateMutability": "view",
		"type": "function"
	},
	{
		"inputs": [
			{
				"internalType": "address",
				"name": "",
				"type": "address"
			},
			{
				"internalType": "uint256",
				"name": "",
				"type": "uint256"
			}
		],
		"name": "ownerLands",
		"outputs": [
			{
				"internalType": "string",
				"name": "",
				"type": "string"
			}
		],
		"stateMutability": "view",
		"type": "function"
	}
]